{"cameraMode":{"drawMode":0,"name":"Shaded","section":"Shading Mode"},"sceneLighting":true,"audioPlay":false,"sceneViewState":{"showFog":true,"showMaterialUpdate":false,"showSkybox":true,"showFlares":true,"showImageEffects":true,"showParticleSystems":true},"in2DMode":false,"pivot":{"x":0.07709026336669922,"y":0.8718637228012085,"z":-1.5808639526367188},"rotation":{"x":0.0032384784426540138,"y":-0.9844232201576233,"z":0.1751679629087448,"w":0.01774735189974308},"size":4.571047306060791,"orthographic":false}